loss_e/__init__.py
loss_e/cli.py
loss_e/compare.py
loss_e/dump.py
loss_e-0.1.0.dist-info/METADATA
loss_e-0.1.0.dist-info/WHEEL
loss_e-0.1.0.dist-info/entry_points.txt
loss_e-0.1.0.dist-info/top_level.txt
loss_e-0.1.0.dist-info/RECORD
