Metadata-Version: 2.4
Name: loss-e
Version: 0.1.0
Summary: lossy compression
Requires-Dist: chz
Requires-Dist: openai
Requires-Dist: filetype
Provides-Extra: dev
